MANIFEST.in
README.md
setup.py
brokerpackager/broker.py
brokerpackager/cli.py
brokerpackager/installer.py
brokerpackager.egg-info/PKG-INFO
brokerpackager.egg-info/SOURCES.txt
brokerpackager.egg-info/dependency_links.txt
brokerpackager.egg-info/requires.txt
brokerpackager.egg-info/top_level.txt
brokerpackager/__pycache__/broker.cpython-36.pyc
brokerpackager/__pycache__/cli.cpython-36.pyc
brokerpackager/__pycache__/installer.cpython-36.pyc
brokerpackager/managers/base.py
brokerpackager/managers/python.py
brokerpackager/managers/r.py
brokerpackager/managers/__pycache__/base.cpython-36.pyc
brokerpackager/managers/__pycache__/python.cpython-36.pyc
brokerpackager/managers/__pycache__/r.cpython-36.pyc
script/broker-packager