Metadata-Version: 1.0
Name: brokerpackager
Version: 0.0.8
Summary: Package Manager based on broker messages
Home-page: UNKNOWN
Author: Big Data
Author-email: bigdata@corp.globo.com
License: MIT
Platform: UNKNOWN
